tviewlang/__init__.py
tviewlang/__main__.py
tviewlang/tviewlang.py
tviewlang-0.0.1.dist-info/LICENSE
tviewlang-0.0.1.dist-info/METADATA
tviewlang-0.0.1.dist-info/WHEEL
tviewlang-0.0.1.dist-info/top_level.txt
tviewlang-0.0.1.dist-info/RECORD
